paprika_api/__init__.py
paprika_api/exceptions.py
paprika_api/groceries.py
paprika_api/notify.py
paprika_api/pantry.py
paprika_api/paprika.py
paprika_api/py.typed
paprika_api/sync.py
paprika_api-0.1.1.dist-info/METADATA
paprika_api-0.1.1.dist-info/WHEEL
paprika_api-0.1.1.dist-info/licenses/LICENSE
paprika_api-0.1.1.dist-info/RECORD
