Metadata-Version: 2.4
Name: paprika-api
Version: 0.1.1
Summary: Unofficial SDK for Paprika API
Project-URL: Repository, https://github.com/smartflutist661/paprika.git
Project-URL: Issues, https://github.com/smartflutist661/paprika/issues
Project-URL: Changelog, https://github.com/smartflutist661/paprika/blob/main/CHANGELOG.md
License-Expression: MIT
License-File: LICENSE
Classifier: Development Status :: 4 - Beta
Classifier: Intended Audience :: Developers
Classifier: Programming Language :: Python :: 3.12
Requires-Python: >=3.12
Requires-Dist: requests~=2.32
